simple_hosting_capacity/__about__.py
simple_hosting_capacity/__init__.py
simple_hosting_capacity/cli.py
simple_hosting_capacity/hosting_capacity_plotter.py
simple_hosting_capacity/simple_hosting_capacity.py
simple_hosting_capacity-0.0.1.dist-info/METADATA
simple_hosting_capacity-0.0.1.dist-info/WHEEL
simple_hosting_capacity-0.0.1.dist-info/entry_points.txt
simple_hosting_capacity-0.0.1.dist-info/licenses/LICENSE
simple_hosting_capacity-0.0.1.dist-info/licenses/LICENSE.txt
simple_hosting_capacity-0.0.1.dist-info/RECORD
